DESCRIPTION.rst
LICENSE
MANIFEST.in
README.md
setup.cfg
setup.py
onedrivesdk_fork.egg-info/PKG-INFO
onedrivesdk_fork.egg-info/SOURCES.txt
onedrivesdk_fork.egg-info/dependency_links.txt
onedrivesdk_fork.egg-info/requires.txt
onedrivesdk_fork.egg-info/top_level.txt
src/onedrivesdk_fork/__init__.py
src/onedrivesdk_fork/async_operation_monitor.py
src/onedrivesdk_fork/auth_provider.py
src/onedrivesdk_fork/auth_provider_base.py
src/onedrivesdk_fork/collection_base.py
src/onedrivesdk_fork/error.py
src/onedrivesdk_fork/http_provider.py
src/onedrivesdk_fork/http_provider_base.py
src/onedrivesdk_fork/http_response.py
src/onedrivesdk_fork/one_drive_object_base.py
src/onedrivesdk_fork/options.py
src/onedrivesdk_fork/request_base.py
src/onedrivesdk_fork/request_builder_base.py
src/onedrivesdk_fork/session.py
src/onedrivesdk_fork/session_base.py
src/onedrivesdk_fork/version.py
src/onedrivesdk_fork/extensions/__init__.py
src/onedrivesdk_fork/extensions/drive_request_builder_helper.py
src/onedrivesdk_fork/extensions/one_drive_client_helper.py
src/onedrivesdk_fork/extensions/onedrivesdk_helper.py
src/onedrivesdk_fork/helpers/GetAuthCodeServer.py
src/onedrivesdk_fork/helpers/__init__.py
src/onedrivesdk_fork/helpers/file_slice.py
src/onedrivesdk_fork/helpers/get_access_token_server.py
src/onedrivesdk_fork/helpers/http_provider_with_proxy.py
src/onedrivesdk_fork/helpers/resource_discovery.py
src/onedrivesdk_fork/model/__init__.py
src/onedrivesdk_fork/model/async_operation_status.py
src/onedrivesdk_fork/model/audio.py
src/onedrivesdk_fork/model/auto_tagged.py
src/onedrivesdk_fork/model/children_collection_page.py
src/onedrivesdk_fork/model/chunked_upload_session_descriptor.py
src/onedrivesdk_fork/model/deleted.py
src/onedrivesdk_fork/model/drive.py
src/onedrivesdk_fork/model/drives_collection_page.py
src/onedrivesdk_fork/model/file.py
src/onedrivesdk_fork/model/file_system_info.py
src/onedrivesdk_fork/model/folder.py
src/onedrivesdk_fork/model/hashes.py
src/onedrivesdk_fork/model/identity.py
src/onedrivesdk_fork/model/identity_set.py
src/onedrivesdk_fork/model/image.py
src/onedrivesdk_fork/model/item.py
src/onedrivesdk_fork/model/item_delta_collection_page.py
