Metadata-Version: 2.1
Name: onedrivesdk-fork
Version: 1.1.14
Summary: Un-Official Python OneDrive SDK for interfacing with OneDrive APIs
Home-page: https://github.com/AtakamaLLC/onedrive-sdk-python
Author: Atakama, LLC
Author-email: support@atakama.com
License: MIT
Keywords: onedrive sdk
Platform: UNKNOWN
Classifier: Development Status :: 4 - Beta
Classifier: Intended Audience :: Developers
Classifier: Topic :: Software Development :: Libraries :: Python Modules
Classifier: License :: OSI Approved :: MIT License
Classifier: Programming Language :: Python :: 3.4
Classifier: Operating System :: OS Independent
Classifier: Operating System :: POSIX
Classifier: Operating System :: Microsoft :: Windows
Classifier: Operating System :: MacOS :: MacOS X
Provides-Extra: tests
Provides-Extra: samples
